rtl/ram.v
module RAM (
    input wire [2:0] addr,
    input wire [3:0] data_in,
    input wire we,
    input wire clk,
    output reg [3:0] data_out
);
    reg [3:0] ram[0:7]; // 8x4 RAM

    always @(posedge clk) begin
        if (we)
            ram[addr] <= data_in;
        else
            data_out <= ram[addr];
    end
endmodule

rtl/rom.v
module ROM (
    input wire [2:0] addr,
    output reg [3:0] data
);
    reg [3:0] rom[0:7]; // 8x4 ROM

    initial begin
        rom[0] = 4'b0000;
        rom[1] = 4'b0001;
        rom[2] = 4'b0010;
        rom[3] = 4'b0011;
        rom[4] = 4'b0100;
        rom[5] = 4'b0101;
        rom[6] = 4'b0110;
        rom[7] = 4'b0111;
    end

    always @(addr) begin
        data = rom[addr];
    end
endmodule

rtl/reg.v
module Register (
    input wire [3:0] D,
    input wire clk,
    input wire reset,
    output reg [3:0] Q
);
    always @(posedge clk or posedge reset) begin
        if (reset)
            Q <= 4'b0000;
        else
            Q <= D;
    end
endmodule

rtl/jkff.v
module JKFlipFlop (
    input wire J,
    input wire K,
    input wire clk,
    input wire reset,
    output reg Q
);
    always @(posedge clk or posedge reset) begin
        if (reset)
            Q <= 0;
        else if (J && ~K)
            Q <= 1;
        else if (~J && K)
            Q <= 0;
        else if (J && K)
            Q <= ~Q;
    end
endmodule

rtl/dff.v
module DFlipFlop (
    input wire D,
    input wire clk,
    input wire reset,
    output reg Q
);
    always @(posedge clk or posedge reset) begin
        if (reset)
            Q <= 0;
        else
            Q <= D;
    end
endmodule

rtl/testbench.v
`timescale 1ns / 1ps

module Testbench;

    // Clock and Reset
    reg clk, reset;

    // D Flip-Flop Signals
    reg D;
    wire Q_DFF;

    // JK Flip-Flop Signals
    reg J, K;
    wire Q_JKFF;

    // Register Signals
    reg [3:0] D_reg;
    wire [3:0] Q_reg;

    // ROM Signals
    reg [2:0] rom_addr;
    wire [3:0] rom_data;

    // RAM Signals
    reg [2:0] ram_addr;
    reg [3:0] ram_data_in;
    wire [3:0] ram_data_out;
    reg we;

    // Instantiate Modules
    DFlipFlop dff (.D(D), .clk(clk), .reset(reset), .Q(Q_DFF));
    JKFlipFlop jkff (.J(J), .K(K), .clk(clk), .reset(reset), .Q(Q_JKFF));
    Register reg4 (.D(D_reg), .clk(clk), .reset(reset), .Q(Q_reg));
    ROM rom (.addr(rom_addr), .data(rom_data));
    RAM ram (.addr(ram_addr), .data_in(ram_data_in), .we(we), .clk(clk), .data_out(ram_data_out));

    // Clock Generation
    always #5 clk = ~clk; // 10ns clock period

    // Test Sequence
    initial begin
        // Initialize signals
        clk = 0; reset = 1; 
        D = 0; J = 0; K = 0; 
        D_reg = 4'b0000; rom_addr = 3'b000; 
        ram_addr = 3'b000; ram_data_in = 4'b0000; we = 0;

        // VCD file generation
        $dumpfile("testbench.vcd"); // Specify VCD file name
        $dumpvars(0, Testbench);   // Dump all signals in the Testbench module

        // Start test sequence
        #10 reset = 0;

        // Test D Flip-Flop
        D = 1; #10; D = 0; #10;

        // Test JK Flip-Flop
        J = 1; K = 0; #10; // Set
        J = 0; K = 1; #10; // Reset
        J = 1; K = 1; #10; // Toggle

        // Test Register
        D_reg = 4'b1010; #10;
        D_reg = 4'b0101; #10;

        // Test ROM
        rom_addr = 3'b000; #10;
        rom_addr = 3'b001; #10;
        rom_addr = 3'b010; #10;

        // Test RAM
        we = 1; ram_addr = 3'b011; ram_data_in = 4'b1111; #10; // Write
        we = 0; ram_addr = 3'b011; #10; // Read

        $finish; // End simulation
    end

    // Monitor Signals
    initial begin
        $monitor("Time=%0d | Reset=%b | D=%b Q_DFF=%b | J=%b K=%b Q_JKFF=%b | D_reg=%b Q_reg=%b | ROM addr=%b data=%b | RAM addr=%b data_in=%b data_out=%b we=%b",
                 $time, reset, D, Q_DFF, J, K, Q_JKFF, D_reg, Q_reg, rom_addr, rom_data, ram_addr, ram_data_in, ram_data_out, we);
    end
endmodule

rtl/testbench.vcd
$date
	Sun Dec  1 15:31:26 2024
$end
$version
	Icarus Verilog
$end
$timescale
	1ps
$end
$scope module Testbench $end
$var wire 4 ! rom_data [3:0] $end
$var wire 4 " ram_data_out [3:0] $end
$var wire 4 # Q_reg [3:0] $end
$var wire 1 $ Q_JKFF $end
$var wire 1 % Q_DFF $end
$var reg 1 & D $end
$var reg 4 ' D_reg [3:0] $end
$var reg 1 ( J $end
$var reg 1 ) K $end
$var reg 1 * clk $end
$var reg 3 + ram_addr [2:0] $end
$var reg 4 , ram_data_in [3:0] $end
$var reg 1 - reset $end
$var reg 3 . rom_addr [2:0] $end
$var reg 1 / we $end
$scope module dff $end
$var wire 1 & D $end
$var wire 1 * clk $end
$var wire 1 - reset $end
$var reg 1 % Q $end
$upscope $end
$scope module jkff $end
$var wire 1 ( J $end
$var wire 1 ) K $end
$var wire 1 * clk $end
$var wire 1 - reset $end
$var reg 1 $ Q $end
$upscope $end
$scope module ram $end
$var wire 3 0 addr [2:0] $end
$var wire 1 * clk $end
$var wire 4 1 data_in [3:0] $end
$var wire 1 / we $end
$var reg 4 2 data_out [3:0] $end
$upscope $end
$scope module reg4 $end
$var wire 4 3 D [3:0] $end
$var wire 1 * clk $end
$var wire 1 - reset $end
$var reg 4 4 Q [3:0] $end
$upscope $end
$scope module rom $end
$var wire 3 5 addr [2:0] $end
$var reg 4 6 data [3:0] $end
$upscope $end
$upscope $end
$enddefinitions $end
#0
$dumpvars
b0 6
b0 5
b0 4
b0 3
bx 2
b0 1
b0 0
0/
b0 .
1-
b0 ,
b0 +
0*
0)
0(
b0 '
0&
0%
0$
b0 #
bx "
b0 !
$end
#5000
1*
#10000
0*
1&
0-
#15000
1%
1*
#20000
0*
0&
#25000
0%
1*
#30000
0*
1(
#35000
1$
1*
#40000
0*
1)
0(
#45000
0$
1*
#50000
0*
1(
#55000
1$
1*
#60000
0*
b1010 '
b1010 3
#65000
b1010 #
b1010 4
0$
1*
#70000
0*
b101 '
b101 3
#75000
1$
b101 #
b101 4
1*
#80000
0*
#85000
0$
1*
#90000
b1 !
b1 6
0*
b1 .
b1 5
#95000
1$
1*
#100000
b10 !
b10 6
0*
b10 .
b10 5
#105000
0$
1*
#110000
0*
b1111 ,
b1111 1
b11 +
b11 0
1/
#115000
1$
1*
#120000
0*
0/
#125000
0$
b1111 "
b1111 2
1*
